{"expireTime":9007200856222243000,"key":"transformer-remark-markdown-ast-15ecc319061fa55944443e28dd3e743f-gatsby-remark-images-","val":{"type":"root","children":[{"type":"paragraph","children":[{"type":"emphasis","children":[{"type":"text","value":"Reputation","position":{"start":{"line":2,"column":2,"offset":2},"end":{"line":2,"column":12,"offset":12},"indent":[]}}],"position":{"start":{"line":2,"column":1,"offset":1},"end":{"line":2,"column":13,"offset":13},"indent":[]}},{"type":"text","value":" was the biggest album of 2018. There’s absolutely no doubt in that. It is also the best selling album of 2017. There’s no doubt in that either. But ever since its release, the media and others have criticized it as being Swift’s biggest flop in her career. But is it really? The simple answer is ","position":{"start":{"line":2,"column":13,"offset":13},"end":{"line":2,"column":310,"offset":310},"indent":[]}},{"type":"strong","children":[{"type":"emphasis","children":[{"type":"text","value":"no","position":{"start":{"line":2,"column":313,"offset":313},"end":{"line":2,"column":315,"offset":315},"indent":[]}}],"position":{"start":{"line":2,"column":312,"offset":312},"end":{"line":2,"column":316,"offset":316},"indent":[]}}],"position":{"start":{"line":2,"column":310,"offset":310},"end":{"line":2,"column":318,"offset":318},"indent":[]}},{"type":"text","value":". But if we dive deeper into the undercurrents, perhaps we would see the essence of the album more clearly.","position":{"start":{"line":2,"column":318,"offset":318},"end":{"line":2,"column":425,"offset":425},"indent":[]}}],"position":{"start":{"line":2,"column":1,"offset":1},"end":{"line":2,"column":425,"offset":425},"indent":[]}},{"type":"heading","depth":2,"children":[{"type":"text","value":"The Drama","position":{"start":{"line":4,"column":4,"offset":430},"end":{"line":4,"column":13,"offset":439},"indent":[]}}],"position":{"start":{"line":4,"column":1,"offset":427},"end":{"line":4,"column":13,"offset":439},"indent":[]}},{"type":"paragraph","children":[{"type":"text","value":"Fast backward three years, the release of ","position":{"start":{"line":6,"column":1,"offset":441},"end":{"line":6,"column":43,"offset":483},"indent":[]}},{"type":"emphasis","children":[{"type":"text","value":"1989","position":{"start":{"line":6,"column":44,"offset":484},"end":{"line":6,"column":48,"offset":488},"indent":[]}}],"position":{"start":{"line":6,"column":43,"offset":483},"end":{"line":6,"column":49,"offset":489},"indent":[]}},{"type":"text","value":" was ","position":{"start":{"line":6,"column":49,"offset":489},"end":{"line":6,"column":54,"offset":494},"indent":[]}},{"type":"strong","children":[{"type":"emphasis","children":[{"type":"text","value":"phenomenal","position":{"start":{"line":6,"column":57,"offset":497},"end":{"line":6,"column":67,"offset":507},"indent":[]}}],"position":{"start":{"line":6,"column":56,"offset":496},"end":{"line":6,"column":68,"offset":508},"indent":[]}}],"position":{"start":{"line":6,"column":54,"offset":494},"end":{"line":6,"column":70,"offset":510},"indent":[]}},{"type":"text","value":". It was heralded as the most iconic, textbook example pop record of the 21st century. Through the sound and delivery, Swift created a world that mixes the vintage and modern, that’s both nostalgic and energetic. A world that places love, and more importantly, the courage to love, on a towering pedestal. ","position":{"start":{"line":6,"column":70,"offset":510},"end":{"line":6,"column":376,"offset":816},"indent":[]}}],"position":{"start":{"line":6,"column":1,"offset":441},"end":{"line":6,"column":376,"offset":816},"indent":[]}},{"type":"paragraph","children":[{"type":"text","value":"But the aftermath of the 1989 era was not pretty.","position":{"start":{"line":8,"column":1,"offset":818},"end":{"line":8,"column":50,"offset":867},"indent":[]}}],"position":{"start":{"line":8,"column":1,"offset":818},"end":{"line":8,"column":50,"offset":867},"indent":[]}},{"type":"paragraph","children":[{"type":"text","value":"As the summer of 2016 unraveled, Swift’s “American Sweetheart” image shattered. Overnight, the media’s perception of her turned from the relatable country princess turned pop queen to a nasty snake suffering from victimhood complex. From Kanye West’s “Famous” (and its music video) to Kim Kardashian’s rapid fire attacks to the god awful breakup with Calvin Harris for songwriting credit claims to the rebound of Tom Hiddleston that lasted a total of 3 seconds, Swift’s reputation suffered and plummeted and crashed. ","position":{"start":{"line":10,"column":1,"offset":869},"end":{"line":10,"column":518,"offset":1386},"indent":[]}}],"position":{"start":{"line":10,"column":1,"offset":869},"end":{"line":10,"column":518,"offset":1386},"indent":[]}},{"type":"paragraph","children":[{"type":"text","value":"The friends she once had, or partied with, or went on the Victoria’s Secret runway with, or made music videos with turned against her. The media that once adored and supported her slandered her. The innocently misled public again showed their viciousness and flooded her social media with the snake emoji. And although it’s impossible for us outsiders to know what really happened underneath the drama, it’s undeniable that the happenstances of that summer seriously affected Swift and fueled the creation of this album.","position":{"start":{"line":12,"column":1,"offset":1388},"end":{"line":12,"column":521,"offset":1908},"indent":[]}}],"position":{"start":{"line":12,"column":1,"offset":1388},"end":{"line":12,"column":521,"offset":1908},"indent":[]}},{"type":"heading","depth":2,"children":[{"type":"text","value":"The Album","position":{"start":{"line":14,"column":4,"offset":1913},"end":{"line":14,"column":13,"offset":1922},"indent":[]}}],"position":{"start":{"line":14,"column":1,"offset":1910},"end":{"line":14,"column":13,"offset":1922},"indent":[]}},{"type":"paragraph","children":[{"type":"text","value":"As such, she took a one year break from releasing material, which was unprecedented to say the least and severely hampered her systematic release schedule. But then came ","position":{"start":{"line":16,"column":1,"offset":1924},"end":{"line":16,"column":171,"offset":2094},"indent":[]}},{"type":"emphasis","children":[{"type":"text","value":"Reputation","position":{"start":{"line":16,"column":172,"offset":2095},"end":{"line":16,"column":182,"offset":2105},"indent":[]}}],"position":{"start":{"line":16,"column":171,"offset":2094},"end":{"line":16,"column":183,"offset":2106},"indent":[]}},{"type":"text","value":", an introspective saga about the aftermath of the collapse of a pop queen’s impeccable reputation— the entire album feels more like Swift’s journey of making peace with the taint in her public image than a traditional love-pop album or diss album. She starts her journey with no sense of remorse whatsoever in I Did Something Bad and Don’t Blame Me:","position":{"start":{"line":16,"column":183,"offset":2106},"end":{"line":16,"column":533,"offset":2456},"indent":[]}}],"position":{"start":{"line":16,"column":1,"offset":1924},"end":{"line":16,"column":533,"offset":2456},"indent":[]}},{"type":"blockquote","children":[{"type":"paragraph","children":[{"type":"text","value":"But if he drops my name, then I owe him nothin'","position":{"start":{"line":17,"column":3,"offset":2459},"end":{"line":17,"column":50,"offset":2506},"indent":[]}},{"type":"break","position":{"start":{"line":17,"column":50,"offset":2506},"end":{"line":18,"column":3,"offset":2512},"indent":[3]}},{"type":"text","value":"And if he spends my change, then he had it comin'","position":{"start":{"line":18,"column":3,"offset":2512},"end":{"line":18,"column":52,"offset":2561},"indent":[]}},{"type":"break","position":{"start":{"line":18,"column":52,"offset":2561},"end":{"line":19,"column":3,"offset":2567},"indent":[3]}},{"type":"text","value":"Don't blame me, love made me crazy","position":{"start":{"line":19,"column":3,"offset":2567},"end":{"line":19,"column":37,"offset":2601},"indent":[]}},{"type":"break","position":{"start":{"line":19,"column":37,"offset":2601},"end":{"line":20,"column":3,"offset":2608},"indent":[3]}},{"type":"text","value":"If it doesn't, you ain't doin' it right   ","position":{"start":{"line":20,"column":3,"offset":2608},"end":{"line":20,"column":45,"offset":2650},"indent":[]}}],"position":{"start":{"line":17,"column":3,"offset":2459},"end":{"line":20,"column":45,"offset":2650},"indent":[3,3,3]}}],"position":{"start":{"line":17,"column":1,"offset":2457},"end":{"line":20,"column":45,"offset":2650},"indent":[1,1,1]}},{"type":"paragraph","children":[{"type":"text","value":"But gradually, that strength she feigns and desire for vengeance seems to fade away, as she scores a new love, a love that is delicate and pure, yet unbreakable by the rumors and defamation. The mid-album songs, such as Gorgeous, King of My Heart, and Dancing With Our Hands Tied, give off a 1989-ish sentiment regarding love, although presented with choppier and darker songwriting. Towards the end of the album, time and love together have been able to heal the scars left behind by the smearing criticisms. In This Is Why We Can’t Have Nice Things, Swift makes snarky remarks that point at specific people:","position":{"start":{"line":22,"column":1,"offset":2652},"end":{"line":22,"column":610,"offset":3261},"indent":[]}}],"position":{"start":{"line":22,"column":1,"offset":2652},"end":{"line":22,"column":610,"offset":3261},"indent":[]}},{"type":"blockquote","children":[{"type":"paragraph","children":[{"type":"text","value":"Friends don't try to trick you","position":{"start":{"line":23,"column":3,"offset":3264},"end":{"line":23,"column":33,"offset":3294},"indent":[]}},{"type":"break","position":{"start":{"line":23,"column":33,"offset":3294},"end":{"line":24,"column":3,"offset":3299},"indent":[3]}},{"type":"text","value":"Get you on the phone and mind-twist you","position":{"start":{"line":24,"column":3,"offset":3299},"end":{"line":24,"column":42,"offset":3338},"indent":[]}},{"type":"break","position":{"start":{"line":24,"column":42,"offset":3338},"end":{"line":25,"column":3,"offset":3344},"indent":[3]}},{"type":"text","value":"But I'm not the only friend you've lost lately","position":{"start":{"line":25,"column":3,"offset":3344},"end":{"line":25,"column":49,"offset":3390},"indent":[]}},{"type":"break","position":{"start":{"line":25,"column":49,"offset":3390},"end":{"line":26,"column":3,"offset":3395},"indent":[3]}},{"type":"text","value":"If only you weren't so shady  ","position":{"start":{"line":26,"column":3,"offset":3395},"end":{"line":26,"column":33,"offset":3425},"indent":[]}}],"position":{"start":{"line":23,"column":3,"offset":3264},"end":{"line":26,"column":33,"offset":3425},"indent":[3,3,3]}}],"position":{"start":{"line":23,"column":1,"offset":3262},"end":{"line":26,"column":33,"offset":3425},"indent":[1,1,1]}},{"type":"paragraph","children":[{"type":"text","value":"Through joking about the agony and injury of the past, she proves that she has grown, that she is indeed beyond the drama, that she has let it go like clouds blown away by the winter wind. Call It What You Want is the final statement that marks the attitude of the Reputation era. Her castle of friends that she used to fortify herself against her insecurities crumbled. Her unpreparedness in the fight forecasted her defeat. She lost her crown, yet in the end, she found something greater. She lost her impeccable reputation, but that’s alright, because she’s stronger now, and the media can really just call it what they want.","position":{"start":{"line":28,"column":1,"offset":3427},"end":{"line":28,"column":629,"offset":4055},"indent":[]}}],"position":{"start":{"line":28,"column":1,"offset":3427},"end":{"line":28,"column":629,"offset":4055},"indent":[]}},{"type":"paragraph","children":[{"type":"text","value":"Sonically speaking, the album mixes elements that are indeed new to Taylor Swift albums, with a greater emphasis on electronic and hip-hop influences. Lyrically speaking, the album is as strong as ever, and Getaway Car is the prime example of that. The entire song tells such a vivid and convincing story of a love that was doomed to fail since its conception. The contrasting colors create an ominous atmosphere while the couplets forge a rhyme scheme that strongly aligns with the beat. The lines easily morph into visuals:","position":{"start":{"line":30,"column":1,"offset":4057},"end":{"line":30,"column":526,"offset":4582},"indent":[]}}],"position":{"start":{"line":30,"column":1,"offset":4057},"end":{"line":30,"column":526,"offset":4582},"indent":[]}},{"type":"blockquote","children":[{"type":"paragraph","children":[{"type":"text","value":"Well, he was runnin' after us, I was screamin’, \"Go, go, go!\"","position":{"start":{"line":31,"column":3,"offset":4585},"end":{"line":31,"column":64,"offset":4646},"indent":[]}},{"type":"break","position":{"start":{"line":31,"column":64,"offset":4646},"end":{"line":32,"column":3,"offset":4652},"indent":[3]}},{"type":"text","value":"But with three of us, honey, it's a sideshow","position":{"start":{"line":32,"column":3,"offset":4652},"end":{"line":32,"column":47,"offset":4696},"indent":[]}}],"position":{"start":{"line":31,"column":3,"offset":4585},"end":{"line":32,"column":47,"offset":4696},"indent":[3]}}],"position":{"start":{"line":31,"column":1,"offset":4583},"end":{"line":32,"column":47,"offset":4696},"indent":[1]}},{"type":"paragraph","children":[{"type":"text","value":"And my personal favorite part comes with the bridge:","position":{"start":{"line":34,"column":1,"offset":4698},"end":{"line":34,"column":53,"offset":4750},"indent":[]}}],"position":{"start":{"line":34,"column":1,"offset":4698},"end":{"line":34,"column":53,"offset":4750},"indent":[]}},{"type":"blockquote","children":[{"type":"paragraph","children":[{"type":"text","value":"I'm in a getaway car","position":{"start":{"line":35,"column":3,"offset":4753},"end":{"line":35,"column":23,"offset":4773},"indent":[]}},{"type":"break","position":{"start":{"line":35,"column":23,"offset":4773},"end":{"line":36,"column":3,"offset":4780},"indent":[3]}},{"type":"text","value":"I left you in a motel bar","position":{"start":{"line":36,"column":3,"offset":4780},"end":{"line":36,"column":28,"offset":4805},"indent":[]}},{"type":"break","position":{"start":{"line":36,"column":28,"offset":4805},"end":{"line":37,"column":3,"offset":4811},"indent":[3]}},{"type":"text","value":"Put the money in a bag and I stole the keys","position":{"start":{"line":37,"column":3,"offset":4811},"end":{"line":37,"column":46,"offset":4854},"indent":[]}},{"type":"break","position":{"start":{"line":37,"column":46,"offset":4854},"end":{"line":38,"column":3,"offset":4860},"indent":[3]}},{"type":"text","value":"That was the last time you ever saw me    ","position":{"start":{"line":38,"column":3,"offset":4860},"end":{"line":38,"column":45,"offset":4902},"indent":[]}}],"position":{"start":{"line":35,"column":3,"offset":4753},"end":{"line":38,"column":45,"offset":4902},"indent":[3,3,3]}}],"position":{"start":{"line":35,"column":1,"offset":4751},"end":{"line":38,"column":45,"offset":4902},"indent":[1,1,1]}},{"type":"paragraph","children":[{"type":"text","value":"She leaves him with no regret. Takes the money and the keys.  Just like how she rode in the car, cried in the car, flew in the car, now she’ll leave in the car. With a light push on the gas pedal and she’s gone, leaving the dusts dancing behind the getaway car. The story is fateful, and brutally honest, the exact same brand of honesty in storytelling that serves as the hallmark of all her songs.","position":{"start":{"line":40,"column":1,"offset":4904},"end":{"line":40,"column":399,"offset":5302},"indent":[]}}],"position":{"start":{"line":40,"column":1,"offset":4904},"end":{"line":40,"column":399,"offset":5302},"indent":[]}},{"type":"paragraph","children":[{"type":"text","value":"In the first half of the album, Swift discusses reputation and dreams of revenge in tracks shrouded with a dark, industrial voltage. Yet in the second half, she continues the iconic vibe of 1989 that pushes the passion of love to momentous heights. She climbed up the ruins of her wounded reputation, and then found salvation in love— that’s a concept that everyone can relate to. Thus, the listening experience is the audience’s journey, along with Swift, to find the exit to the pain and the gleaming sun of a newfound comfort.","position":{"start":{"line":42,"column":1,"offset":5304},"end":{"line":42,"column":530,"offset":5833},"indent":[]}}],"position":{"start":{"line":42,"column":1,"offset":5304},"end":{"line":42,"column":530,"offset":5833},"indent":[]}},{"type":"paragraph","children":[{"type":"image","title":null,"url":"https://www.philly.com/resizer/aDjqN0LW_l-NmG96oVQuPCcpjX8=/1400x0/center/middle/arc-anglerfish-arc2-prod-pmn.s3.amazonaws.com/public/T45JUACWFNFHJLT23COTJZ3K6M.jpg","alt":"Section","position":{"start":{"line":44,"column":1,"offset":5835},"end":{"line":44,"column":177,"offset":6011},"indent":[]}}],"position":{"start":{"line":44,"column":1,"offset":5835},"end":{"line":44,"column":177,"offset":6011},"indent":[]}},{"type":"heading","depth":2,"children":[{"type":"text","value":"The Verdict","position":{"start":{"line":46,"column":4,"offset":6016},"end":{"line":46,"column":15,"offset":6027},"indent":[]}}],"position":{"start":{"line":46,"column":1,"offset":6013},"end":{"line":46,"column":15,"offset":6027},"indent":[]}},{"type":"paragraph","children":[{"type":"text","value":"Speaking of success, ","position":{"start":{"line":48,"column":1,"offset":6029},"end":{"line":48,"column":22,"offset":6050},"indent":[]}},{"type":"emphasis","children":[{"type":"text","value":"Reputation","position":{"start":{"line":48,"column":23,"offset":6051},"end":{"line":48,"column":33,"offset":6061},"indent":[]}}],"position":{"start":{"line":48,"column":22,"offset":6050},"end":{"line":48,"column":34,"offset":6062},"indent":[]}},{"type":"text","value":" was a gigantic commercial success. In a world with streaming dominating the scene, Taylor Swift is one of the few artists that can sell a million copies in the first week. Aside from sales, the Reputation Stadium Tour grossed 345.7 million dollars, which is 100 million more than the 1989 World Tour with 50% less shows. ","position":{"start":{"line":48,"column":34,"offset":6062},"end":{"line":48,"column":356,"offset":6384},"indent":[]}},{"type":"emphasis","children":[{"type":"text","value":"Also making it the ","position":{"start":{"line":48,"column":357,"offset":6385},"end":{"line":48,"column":376,"offset":6404},"indent":[]}},{"type":"strong","children":[{"type":"text","value":"second highest","position":{"start":{"line":48,"column":378,"offset":6406},"end":{"line":48,"column":392,"offset":6420},"indent":[]}}],"position":{"start":{"line":48,"column":376,"offset":6404},"end":{"line":48,"column":394,"offset":6422},"indent":[]}},{"type":"text","value":" per show gross in the history of concert tours","position":{"start":{"line":48,"column":394,"offset":6422},"end":{"line":48,"column":441,"offset":6469},"indent":[]}}],"position":{"start":{"line":48,"column":356,"offset":6384},"end":{"line":48,"column":442,"offset":6470},"indent":[]}},{"type":"text","value":". The production of the tour doubtlessly makes it the best of 2018, with marvelous performances from eras old and new, incredible choreography, and stunning stage design and fireworks. Without essentially any promotion, the fact that Reputation accomplished all of the above is absolutely phenomenal.","position":{"start":{"line":48,"column":442,"offset":6470},"end":{"line":48,"column":742,"offset":6770},"indent":[]}}],"position":{"start":{"line":48,"column":1,"offset":6029},"end":{"line":48,"column":742,"offset":6770},"indent":[]}},{"type":"paragraph","children":[{"type":"text","value":"Overall, ","position":{"start":{"line":50,"column":1,"offset":6772},"end":{"line":50,"column":10,"offset":6781},"indent":[]}},{"type":"emphasis","children":[{"type":"text","value":"Reputation","position":{"start":{"line":50,"column":11,"offset":6782},"end":{"line":50,"column":21,"offset":6792},"indent":[]}}],"position":{"start":{"line":50,"column":10,"offset":6781},"end":{"line":50,"column":22,"offset":6793},"indent":[]}},{"type":"text","value":" is an unmissable album from 2017, and I was rather speechless when it wasn’t nominated for Album of the Year at the 2019 Grammys, especially since it’s the first year of expanded nominations. In fact, similar to ","position":{"start":{"line":50,"column":22,"offset":6793},"end":{"line":50,"column":235,"offset":7006},"indent":[]}},{"type":"emphasis","children":[{"type":"text","value":"Speak Now","position":{"start":{"line":50,"column":236,"offset":7007},"end":{"line":50,"column":245,"offset":7016},"indent":[]}}],"position":{"start":{"line":50,"column":235,"offset":7006},"end":{"line":50,"column":246,"offset":7017},"indent":[]}},{"type":"text","value":", ","position":{"start":{"line":50,"column":246,"offset":7017},"end":{"line":50,"column":248,"offset":7019},"indent":[]}},{"type":"emphasis","children":[{"type":"text","value":"Reputation","position":{"start":{"line":50,"column":249,"offset":7020},"end":{"line":50,"column":259,"offset":7030},"indent":[]}}],"position":{"start":{"line":50,"column":248,"offset":7019},"end":{"line":50,"column":260,"offset":7031},"indent":[]}},{"type":"text","value":" did not receive any General Field nominations, and like ","position":{"start":{"line":50,"column":260,"offset":7031},"end":{"line":50,"column":317,"offset":7088},"indent":[]}},{"type":"emphasis","children":[{"type":"text","value":"Red","position":{"start":{"line":50,"column":318,"offset":7089},"end":{"line":50,"column":321,"offset":7092},"indent":[]}}],"position":{"start":{"line":50,"column":317,"offset":7088},"end":{"line":50,"column":322,"offset":7093},"indent":[]}},{"type":"text","value":", it did not win a single Grammy. This might mean that ","position":{"start":{"line":50,"column":322,"offset":7093},"end":{"line":50,"column":377,"offset":7148},"indent":[]}},{"type":"emphasis","children":[{"type":"text","value":"Reputation","position":{"start":{"line":50,"column":378,"offset":7149},"end":{"line":50,"column":388,"offset":7159},"indent":[]}}],"position":{"start":{"line":50,"column":377,"offset":7148},"end":{"line":50,"column":389,"offset":7160},"indent":[]}},{"type":"text","value":" is a flop according to Swift’s standards, or at least, the Old Taylor’s standards. I mean, remember how she went on to make ","position":{"start":{"line":50,"column":389,"offset":7160},"end":{"line":50,"column":514,"offset":7285},"indent":[]}},{"type":"emphasis","children":[{"type":"text","value":"1989","position":{"start":{"line":50,"column":515,"offset":7286},"end":{"line":50,"column":519,"offset":7290},"indent":[]}}],"position":{"start":{"line":50,"column":514,"offset":7285},"end":{"line":50,"column":520,"offset":7291},"indent":[]}},{"type":"text","value":" to slap the Recording Academy in the face after her defeat with ","position":{"start":{"line":50,"column":520,"offset":7291},"end":{"line":50,"column":585,"offset":7356},"indent":[]}},{"type":"emphasis","children":[{"type":"text","value":"Red","position":{"start":{"line":50,"column":586,"offset":7357},"end":{"line":50,"column":589,"offset":7360},"indent":[]}}],"position":{"start":{"line":50,"column":585,"offset":7356},"end":{"line":50,"column":590,"offset":7361},"indent":[]}},{"type":"text","value":"? But then again, the Old Taylor is dead, and perhaps she is simply tired of the massive routine promotional effort behind a Grammy run. With 10 Grammys in her pocket and gracefully marching into her late 20s, maybe what we are seeing is, in addition to a sincere reflection of a lost prestige, a growth and maturity signifying that she’s unbothered by cosmetics like these. ","position":{"start":{"line":50,"column":590,"offset":7361},"end":{"line":50,"column":965,"offset":7736},"indent":[]}}],"position":{"start":{"line":50,"column":1,"offset":6772},"end":{"line":50,"column":965,"offset":7736},"indent":[]}},{"type":"paragraph","children":[{"type":"text","value":"However, looking at the other nominees this year in the General Field, we are seeing a growing dominance of hip-hop. Whether this is due to the rise of streaming platforms or the Recording Academy’s attempt at \"inclusivity,\" it’s undeniable that hip-hop is becoming the new “pop.” No matter how some dislike the new sound, or how the promotion is lacking, it’s hard to deny that ","position":{"start":{"line":52,"column":1,"offset":7738},"end":{"line":52,"column":380,"offset":8117},"indent":[]}},{"type":"emphasis","children":[{"type":"text","value":"Reputation","position":{"start":{"line":52,"column":381,"offset":8118},"end":{"line":52,"column":391,"offset":8128},"indent":[]}}],"position":{"start":{"line":52,"column":380,"offset":8117},"end":{"line":52,"column":392,"offset":8129},"indent":[]}},{"type":"text","value":" is a successful pop record that totally deserves to be nominated, and entries like End Game and Delicate totally merit a nomination and even the award.","position":{"start":{"line":52,"column":392,"offset":8129},"end":{"line":52,"column":544,"offset":8281},"indent":[]}}],"position":{"start":{"line":52,"column":1,"offset":7738},"end":{"line":52,"column":544,"offset":8281},"indent":[]}},{"type":"paragraph","children":[{"type":"text","value":"Or perhaps ","position":{"start":{"line":54,"column":1,"offset":8283},"end":{"line":54,"column":12,"offset":8294},"indent":[]}},{"type":"emphasis","children":[{"type":"text","value":"Reputation’s","position":{"start":{"line":54,"column":13,"offset":8295},"end":{"line":54,"column":25,"offset":8307},"indent":[]}}],"position":{"start":{"line":54,"column":12,"offset":8294},"end":{"line":54,"column":26,"offset":8308},"indent":[]}},{"type":"text","value":" “flop” is a portrayal of a larger phenomenon: the decline of pop as a genre. A phenomenon that started with The Chainsmokers’ Closer, which marked the beginning a trend of mixing of EDM into pop that produced a series of forgettable releases and unexciting tunes that sound all too similar. Somewhere in there, pop lost its appeal. And with many of the major pop stars on hiatus, the necessity of the revival of pop is imminent.","position":{"start":{"line":54,"column":26,"offset":8308},"end":{"line":54,"column":455,"offset":8737},"indent":[]}}],"position":{"start":{"line":54,"column":1,"offset":8283},"end":{"line":54,"column":455,"offset":8737},"indent":[]}},{"type":"paragraph","children":[{"type":"text","value":"In this sense, Taylor Swift is like a single-handed warrior that tries to save the waning pop scene besieged by hip-hop but is left aside. The road for pop will become narrower and more limited; an average hip-hop album might score good reception with the push of streaming platforms, but a high-quality pop record might not attain comparable success. In the coming years, pop stars will have to seek different sounds or bring something new to standout in the sea of mediocre hip-hop.","position":{"start":{"line":56,"column":1,"offset":8739},"end":{"line":56,"column":485,"offset":9223},"indent":[]}}],"position":{"start":{"line":56,"column":1,"offset":8739},"end":{"line":56,"column":485,"offset":9223},"indent":[]}}],"position":{"start":{"line":1,"column":1,"offset":0},"end":{"line":57,"column":1,"offset":9224}}}}